.github/pull_request_template.md
CHANGELOG.md
README.md
requirements-poetry.txt
clickup_to_jira/__init__.py
clickup_to_jira/comment.py
clickup_to_jira/converter.py
clickup_to_jira/handlers/__init__.py
clickup_to_jira/handlers/clickup.py
clickup_to_jira/handlers/jira.py
clickup_to_jira/scripts/__init__.py
clickup_to_jira/scripts/migrate.py
clickup_to_jira/ticket.py
clickup_to_jira/utils.py
clickup_to_jira-1.1.2.dist-info/LICENSE
clickup_to_jira-1.1.2.dist-info/METADATA
clickup_to_jira-1.1.2.dist-info/WHEEL
clickup_to_jira-1.1.2.dist-info/entry_points.txt
clickup_to_jira-1.1.2.dist-info/RECORD
