Metadata-Version: 2.1
Name: clickup_to_jira
Version: 1.1.2
Summary: This project is a small utility that helps migrating tasks from ClickUp to JIRA.
License: MIT
Keywords: clickup_to_jira
Author: Antonis Markoulis
Author-email: amarkoulis@hotmail.com
Requires-Python: >=3.8.0,<4.0.0
Classifier: License :: OSI Approved :: MIT License
Classifier: Programming Language :: Python :: 3
Classifier: Programming Language :: Python :: 3.8
Classifier: Programming Language :: Python :: 3.9
Classifier: Programming Language :: Python :: 3.10
Classifier: Programming Language :: Python :: 3.11
Classifier: Programming Language :: Python :: 3.12
Requires-Dist: jira (==3.8.0)
Requires-Dist: mistletoe (==1.4.0)
Requires-Dist: pyclickup (==0.1.4)
Requires-Dist: python-dotenv (==1.0.0)
Requires-Dist: requests (==2.32.3)
